iotile_analytics/__init__.py
iotile_analytics/interactive/__init__.py
iotile_analytics/interactive/app.py
iotile_analytics/interactive/viewer_base.py
iotile_analytics/interactive/viewer_histogram.py
iotile_analytics/interactive/viewer_loglog.py
iotile_analytics/interactive/viewer_piechart.py
iotile_analytics/interactive/viewer_timeselect.py
iotile_analytics/interactive/reports/__init__.py
iotile_analytics/interactive/reports/action_report.py
iotile_analytics/interactive/reports/analysis_template.py
iotile_analytics/interactive/reports/branded_report.py
iotile_analytics/interactive/reports/cloud_uploader.py
iotile_analytics/interactive/reports/info_report.py
iotile_analytics/interactive/reports/multiple_source_info.py
iotile_analytics/interactive/reports/report.py
iotile_analytics/interactive/reports/stream_report.py
iotile_analytics/interactive/reports/handlers/__init__.py
iotile_analytics/interactive/reports/handlers/base_handler.py
iotile_analytics/interactive/reports/handlers/file_handler.py
iotile_analytics/interactive/reports/handlers/stdout_handler.py
iotile_analytics/interactive/reports/handlers/streaming_web_push_handler.py
iotile_analytics/interactive/reports/handlers/web_push_handler.py
iotile_analytics/interactive/reports/handlers/zip_handler.py
iotile_analytics/interactive/reports/templates/branded_footer.html
iotile_analytics/interactive/reports/templates/branded_header.html
iotile_analytics/interactive/reports/templates/jquery-3.3.1.min.js
iotile_analytics/interactive/reports/templates/report_style.css
iotile_analytics/interactive/reports/templates/unhosted_file.html
iotile_analytics/interactive/scripts/__init__.py
iotile_analytics/interactive/scripts/analytics_host.py
iotile_analytics_interactive-0.6.3.dist-info/LICENSE.md
iotile_analytics_interactive-0.6.3.dist-info/METADATA
iotile_analytics_interactive-0.6.3.dist-info/WHEEL
iotile_analytics_interactive-0.6.3.dist-info/entry_points.txt
iotile_analytics_interactive-0.6.3.dist-info/top_level.txt
iotile_analytics_interactive-0.6.3.dist-info/RECORD
